H5Gizmos/__init__.py
H5Gizmos/js/H5Gizmos.js
H5Gizmos/js/screen_capture_canvas.js
H5Gizmos/python/PageGizmo.py
H5Gizmos/python/__init__.py
H5Gizmos/python/copy_server.py
H5Gizmos/python/custom_page.py
H5Gizmos/python/examine.py
H5Gizmos/python/file_selector.py
H5Gizmos/python/gizmo_launch_url.py
H5Gizmos/python/gizmo_link.py
H5Gizmos/python/gizmo_script_support.py
H5Gizmos/python/gizmo_server.py
H5Gizmos/python/gz_components.py
H5Gizmos/python/gz_get_blob.py
H5Gizmos/python/gz_jQuery.py
H5Gizmos/python/gz_module_support.py
H5Gizmos/python/gz_parent_protocol.py
H5Gizmos/python/gz_plotly.py
H5Gizmos/python/gz_resources.py
H5Gizmos/python/gz_screencap.py
H5Gizmos/python/gz_tools.py
H5Gizmos/python/hex_codec.py
H5Gizmos/python/jupyter_gizmo_support.py
H5Gizmos/python/oldPageGizmo.py
H5Gizmos/python/qd_file_browser.py
H5Gizmos/python/scripts/__init__.py
H5Gizmos/python/scripts/hello_env.py
H5Gizmos/python/scripts/lorenz.py
H5Gizmos/python/scripts/qd_chat.py
H5Gizmos/python/scripts/show_binary.py
H5Gizmos/python/test/__init__.py
H5Gizmos/python/test/test_H5Gizmos.py
H5Gizmos/python/test/test_components.py
H5Gizmos/python/test/test_gizmo_server.py
H5Gizmos/python/test/test_gz_resources.py
H5Gizmos/python/test/test_hex_codec.py
H5Gizmos/static/JQuery_overrides.css
H5Gizmos/static/gizmo_link_start.html
H5Gizmos/static/gizmo_link_support.js
H5Gizmos/static/gizmo_style.css
H5Gizmos/static/icon.png
H5Gizmos/static/logo.svg
H5Gizmos/static/save_icon.png
H5Gizmos/static/jquery-ui-1.12.1/AUTHORS.txt
H5Gizmos/static/jquery-ui-1.12.1/LICENSE.txt
H5Gizmos/static/jquery-ui-1.12.1/index.html
H5Gizmos/static/jquery-ui-1.12.1/jquery-ui.css
H5Gizmos/static/jquery-ui-1.12.1/jquery-ui.js
H5Gizmos/static/jquery-ui-1.12.1/jquery-ui.min.css
H5Gizmos/static/jquery-ui-1.12.1/jquery-ui.min.js
H5Gizmos/static/jquery-ui-1.12.1/jquery-ui.structure.css
H5Gizmos/static/jquery-ui-1.12.1/jquery-ui.structure.min.css
H5Gizmos/static/jquery-ui-1.12.1/jquery-ui.theme.css
h5gizmos-0.1.17.dist-info/licenses/LICENSE
h5gizmos-0.1.17.dist-info/METADATA
h5gizmos-0.1.17.dist-info/WHEEL
h5gizmos-0.1.17.dist-info/entry_points.txt
h5gizmos-0.1.17.dist-info/top_level.txt
h5gizmos-0.1.17.dist-info/RECORD
