Metadata-Version: 2.4
Name: H5Gizmos
Version: 0.1.17
Summary: Tools for building interactive graphical interfaces for applications using browser technology and HTML5
Home-page: https://github.com/AaronWatters/H5Gizmos
Author: Aaron Watters
Author-email: awatters@flatironinstitute.org
Requires-Python: >=3.6
License-File: LICENSE
Requires-Dist: numpy
Requires-Dist: aiohttp
Requires-Dist: imageio
Requires-Dist: matplotlib>=2.0.0
Requires-Dist: jupyter-server-proxy
Dynamic: author
Dynamic: author-email
Dynamic: description
Dynamic: description-content-type
Dynamic: home-page
Dynamic: license-file
Dynamic: requires-dist
Dynamic: requires-python
Dynamic: summary
